litecoinutils/__init__.py
litecoinutils/bech32.py
litecoinutils/constants.py
litecoinutils/keys.py
litecoinutils/proxy.py
litecoinutils/script.py
litecoinutils/setup.py
litecoinutils/transactions.py
litecoinutils/utils.py
litecoin_utils-0.5.5.dist-info/LICENSE
litecoin_utils-0.5.5.dist-info/METADATA
litecoin_utils-0.5.5.dist-info/WHEEL
litecoin_utils-0.5.5.dist-info/top_level.txt
litecoin_utils-0.5.5.dist-info/RECORD
