Metadata-Version: 2.1
Name: litecoin-utils
Version: 0.5.5
Summary: Litecoin utility functions
Home-page: https://github.com/karask/python-litecoin-utils
Author: Konstantinos Karasavvas
Author-email: kkarasavvas@gmail.com
License: AGPLv3
Keywords: litecoin library utilities tools
Platform: UNKNOWN
License-File: LICENSE
Requires-Dist: base58check (==1.0.2)
Requires-Dist: ecdsa (==0.17.0)
Requires-Dist: python-bitcoinrpc (==1.0)
Requires-Dist: sympy (==1.3)
